{
  "background": {
    "current": "mainbg_an",
    "previous": "mainbg_an"
  },
  "information": {
    "fairyPose": 2,
    "fairyFace": 4,
    "byCountry": {
      "1": {
        "fairyCharacterId": 117,
        "fairyPose": 1,
        "fairyFace": 4
      },
      "2": {
        "fairyCharacterId": 120,
        "fairyPose": 1,
        "fairyFace": 8
      },
      "3": {
        "fairyCharacterId": 111,
        "fairyPose": 2,
        "fairyFace": 4
      }
    },
    "message": {
      "text": "Welcome back.",
      "color": "0xFFFFFF",
      "size": 20
    }
  }
}
